json_to_dataclass.py
json_to_dataclass-1.0.0.dist-info/LICENSE
json_to_dataclass-1.0.0.dist-info/METADATA
json_to_dataclass-1.0.0.dist-info/WHEEL
json_to_dataclass-1.0.0.dist-info/RECORD
