Metadata-Version: 2.3
Name: json-to-dataclass
Version: 1.0.0
Summary: Useful tool for mapping out dataclasses based on JSON structure with typing
Author: Lifelite
Author-email: j.t.huntsman@gmail.com
Requires-Python: >=3.12,<4.0
Classifier: Programming Language :: Python :: 3
Classifier: Programming Language :: Python :: 3.12
Classifier: Programming Language :: Python :: 3.13
